torchreinforce/__init__.py
torchreinforce/output.py
torchreinforce/reinforce.py
torchreinforce/distributions/__init__.py
torchreinforce/distributions/base.py
torchreinforce/distributions/categorical.py
torchreinforce/distributions/wrapper.py
torchreinforce/tests/__init__.py
torchreinforce/tests/grad_test.py
torchreinforce-0.1.0.dist-info/LICENSE
torchreinforce-0.1.0.dist-info/METADATA
torchreinforce-0.1.0.dist-info/WHEEL
torchreinforce-0.1.0.dist-info/top_level.txt
torchreinforce-0.1.0.dist-info/RECORD
