Metadata-Version: 2.1
Name: torchreinforce
Version: 0.1.0
Summary: A pythonic implementation of the REINFORCE algorithm that is actually fun to use
Home-page: https://github.com/galatolofederico/torchreinforce
Author: Federico A. Galatolo
Author-email: galatolo.federico@gmail.com
License: UNKNOWN
Platform: UNKNOWN
Classifier: Programming Language :: Python :: 3.6
Classifier: License :: OSI Approved :: GNU General Public License v3 (GPLv3)
Classifier: Operating System :: OS Independent
Classifier: Topic :: Scientific/Engineering :: Artificial Intelligence
Classifier: Intended Audience :: Science/Research
Classifier: Development Status :: 4 - Beta
Requires-Dist: torch
Requires-Dist: numpy
